{"data":{"Year":["2018","2018","2018","2018","2018","2018","2018","2018","2018","2018","2018","2018","2018","2018","2018","2018","2018","2018","2018","2018","2018","2018"],"concept.REF_AREA":[null,null,null,"code.KG05","code.KG03","code.KG02","code.KG04","code.KG06","code.KG07","code.KG08","code.KG11","code.KG21",null,null,null,null,null,null,null,null,null,null],"concept.URBANISATION":[null,"code.U","code.R",null,null,null,null,null,null,null,null,null,null,null,null,null,null,null,null,null,null,null],"concept.INCOME_WEALTH_QUANTILE":[null,null,null,null,null,null,null,null,null,null,null,null,null,null,null,null,null,"code.Q1","code.Q2","code.Q3","code.Q4","code.Q5"],"concept.EDUCATION_LEV":[null,null,null,null,null,null,null,null,null,null,null,null,"code.ISCED11_1","code.ISCED11_2","code.ISCED11_3","code.ISCED11_4","code.ISCED11_5",null,null,null,null,null],"Value":[96.3,96.1,96.5,99.6,93.4,99.1,99.4,99.1,99.8,91.6,95.7,96.8,92.1,94.7,97.4,96.6,95.1,97.2,95.9,96.5,96.4,95.7]},"edges":[]}