[{"Year":2018,"Value":364.0,"SERIES":"_L_KG_020401_1A"},{"Year":2019,"Value":354.0,"SERIES":"_L_KG_020401_1A"},{"Year":2020,"Value":359.0,"SERIES":"_L_KG_020401_1A"},{"Year":2021,"Value":356.0,"SERIES":"_L_KG_020401_1A"},{"Year":2022,"Value":368.0,"SERIES":"_L_KG_020401_1A"},{"Year":2023,"Value":355.0,"SERIES":"_L_KG_020401_1A"},{"Year":2024,"Value":40.2,"SERIES":"_L_KG_020401_1A"},{"Year":2018,"Value":25.0,"SERIES":"_L_KG_020401_1B"},{"Year":2019,"Value":25.0,"SERIES":"_L_KG_020401_1B"},{"Year":2020,"Value":22.0,"SERIES":"_L_KG_020401_1B"},{"Year":2021,"Value":25.0,"SERIES":"_L_KG_020401_1B"},{"Year":2022,"Value":27.0,"SERIES":"_L_KG_020401_1B"},{"Year":2023,"Value":25.0,"SERIES":"_L_KG_020401_1B"},{"Year":2024,"Value":27.0,"SERIES":"_L_KG_020401_1B"}]