[{"Year":"2012","Value":975,"SERIES":"IT_MOB_2GNTWK"},{"Year":"2013","Value":976,"SERIES":"IT_MOB_2GNTWK"},{"Year":"2014","Value":977,"SERIES":"IT_MOB_2GNTWK"},{"Year":"2015","Value":978,"SERIES":"IT_MOB_2GNTWK"},{"Year":"2016","Value":990,"SERIES":"IT_MOB_2GNTWK"},{"Year":"2017","Value":991,"SERIES":"IT_MOB_2GNTWK"},{"Year":"2018","Value":992,"SERIES":"IT_MOB_2GNTWK"},{"Year":"2019","Value":993,"SERIES":"IT_MOB_2GNTWK"},{"Year":"2020","Value":990,"SERIES":"IT_MOB_2GNTWK"},{"Year":"2012","Value":463,"SERIES":"IT_MOB_3GNTWK"},{"Year":"2013","Value":510,"SERIES":"IT_MOB_3GNTWK"},{"Year":"2014","Value":570,"SERIES":"IT_MOB_3GNTWK"},{"Year":"2015","Value":590,"SERIES":"IT_MOB_3GNTWK"},{"Year":"2016","Value":600,"SERIES":"IT_MOB_3GNTWK"},{"Year":"2017","Value":750,"SERIES":"IT_MOB_3GNTWK"},{"Year":"2018","Value":880,"SERIES":"IT_MOB_3GNTWK"},{"Year":"2019","Value":910,"SERIES":"IT_MOB_3GNTWK"},{"Year":"2020","Value":893,"SERIES":"IT_MOB_3GNTWK"},{"Year":"2014","Value":5,"SERIES":"IT_MOB_4GNTWK"},{"Year":"2015","Value":16,"SERIES":"IT_MOB_4GNTWK"},{"Year":"2016","Value":400,"SERIES":"IT_MOB_4GNTWK"},{"Year":"2017","Value":500,"SERIES":"IT_MOB_4GNTWK"},{"Year":"2018","Value":700,"SERIES":"IT_MOB_4GNTWK"},{"Year":"2019","Value":850,"SERIES":"IT_MOB_4GNTWK"},{"Year":"2020","Value":819,"SERIES":"IT_MOB_4GNTWK"}]