{"Year":["2018","2018","2018","2018","2018","2018","2018","2018","2018","2018","2018","2018","2018","2018","2018","2018","2018","2018","2018","2018","2018","2018","2018","2018","2018","2018","2018","2018","2018","2018","2018","2018"],"Reference area":[null,null,null,"Batken","Jalal-Abad","Issyk-Kul","Naryn","Osh","Talas","Chui","Bishkek (city)","Osh (city)",null,null,null,null,null,null,null,null,null,null,null,null,null,null,null,null,null,null,null,null],"Age":["15 to 49 years old","15 to 49 years old","15 to 49 years old","15 to 49 years old","15 to 49 years old","15 to 49 years old","15 to 49 years old","15 to 49 years old","15 to 49 years old","15 to 49 years old","15 to 49 years old","15 to 49 years old","15 to 19 years old","15 to 17 years old","18 to 19 years old","20 to 24 years old","25 to 29 years old","30 to 34 years old","35 to 39 years old","40 to 44 years old","45 to 49 years old","15 to 49 years old","15 to 49 years old","15 to 49 years old","15 to 49 years old","15 to 49 years old","15 to 49 years old","15 to 49 years old","15 to 49 years old","15 to 49 years old","15 to 49 years old","15 to 49 years old"],"Degree of urbanisation":[null,"Urban","Rural",null,null,null,null,null,null,null,null,null,null,null,null,null,null,null,null,null,null,null,null,null,null,null,null,null,null,null,null,null],"Income or wealth quantile":[null,null,null,null,null,null,null,null,null,null,null,null,null,null,null,null,null,null,null,null,null,null,null,null,null,null,null,"Quintile 1 (poorest)","Quintile 2","Quintile 3","Quintile 4","Quintile 5 (richest)"],"Education level":[null,null,null,null,null,null,null,null,null,null,null,null,null,null,null,null,null,null,null,null,null,"Primary education","Lower secondary education","Upper secondary education","Post-secondary non-tertiary education",null,null,null,null,null,null,null],"Disability status":[null,null,null,null,null,null,null,null,null,null,null,null,null,null,null,null,null,null,null,null,null,null,null,null,null,"Persons with disability","Persons without disability",null,null,null,null,null],"Value":[7.7,7.9,7.6,0.4,7.3,1.7,2.8,6.5,5.0,16.6,8.7,7.0,6.5,5.7,8.3,9.1,7.1,8.8,8.7,6.4,7.0,14.0,5.9,6.9,8.2,20.7,7.6,6.0,6.7,9.7,7.1,8.8]}