{"Year":["2018","2018","2018","2018","2018","2018","2018","2018","2018","2018","2018","2018","2018","2018","2018","2018","2018","2018","2018","2018","2018","2018","2018","2018","2018","2018","2018","2018","2018","2018","2018","2018","2018","2018","2018","2018","2018","2018","2018","2018"],"Series":["SP_DYN_MRBF15","SP_DYN_MRBF15","SP_DYN_MRBF15","SP_DYN_MRBF15","SP_DYN_MRBF15","SP_DYN_MRBF15","SP_DYN_MRBF15","SP_DYN_MRBF15","SP_DYN_MRBF15","SP_DYN_MRBF15","SP_DYN_MRBF15","SP_DYN_MRBF15","SP_DYN_MRBF15","SP_DYN_MRBF15","SP_DYN_MRBF15","SP_DYN_MRBF15","SP_DYN_MRBF15","SP_DYN_MRBF15","SP_DYN_MRBF15","SP_DYN_MRBF15","SP_DYN_MRBF18","SP_DYN_MRBF18","SP_DYN_MRBF18","SP_DYN_MRBF18","SP_DYN_MRBF18","SP_DYN_MRBF18","SP_DYN_MRBF18","SP_DYN_MRBF18","SP_DYN_MRBF18","SP_DYN_MRBF18","SP_DYN_MRBF18","SP_DYN_MRBF18","SP_DYN_MRBF18","SP_DYN_MRBF18","SP_DYN_MRBF18","SP_DYN_MRBF18","SP_DYN_MRBF18","SP_DYN_MRBF18","SP_DYN_MRBF18","SP_DYN_MRBF18"],"REF_AREA":[null,"KG05","KG03","KG02","KG04","KG06","KG07","KG08","KG11","KG21",null,null,null,null,null,null,null,null,null,null,null,"KG05","KG03","KG02","KG04","KG06","KG07","KG08","KG11","KG21",null,null,null,null,null,null,null,null,null,null],"INCOME_WEALTH_QUANTILE":[null,null,null,null,null,null,null,null,null,null,null,null,null,null,null,"Q1","Q2","Q3","Q4","Q5",null,null,null,null,null,null,null,null,null,null,null,null,null,null,null,"Q1","Q2","Q3","Q4","Q5"],"EDUCATION_LEV":[null,null,null,null,null,null,null,null,null,null,"ISCED11_2","ISCED11_3","ISCED11_4","ISCED11_5",null,null,null,null,null,null,null,null,null,null,null,null,null,null,null,null,"ISCED11_2","ISCED11_3","ISCED11_4","ISCED11_5",null,null,null,null,null,null],"DISABILITY_STATUS":[null,null,null,null,null,null,null,null,null,null,null,null,null,null,"PWD",null,null,null,null,null,null,null,null,null,null,null,null,null,null,null,null,null,null,null,"PWD",null,null,null,null,null],"Value":[0.3,0.0,0.0,0.0,0.0,0.0,2.8,0.0,1.0,0.0,0.6,0.8,0.0,0.0,0.3,0.0,0.4,0.0,0.0,1.1,12.9,14.4,13.6,11.5,18.4,18.3,16.5,11.6,5.3,13.2,30.3,21.3,6.0,2.6,12.7,11.8,19.7,14.4,12.5,6.4]}